[
  {
    "name": "project1.png",
    "path": "images/project1.png",
    "size": 1633069,
    "created": 1765176338.0189881
  },
  {
    "name": "project1.4.jpg",
    "path": "images/project1.4.jpg",
    "size": 34245,
    "created": 1765176338.0092168
  },
  {
    "name": "project1.3.png",
    "path": "images/project1.3.png",
    "size": 1364573,
    "created": 1765176338.0077755
  },
  {
    "name": "project1.2.png",
    "path": "images/project1.2.png",
    "size": 1263516,
    "created": 1765176337.997091
  },
  {
    "name": "project1.1.png",
    "path": "images/project1.1.png",
    "size": 1403940,
    "created": 1765176337.9866722
  },
  {
    "name": "avatar.jpg",
    "path": "images/avatar.jpg",
    "size": 66171,
    "created": 1763796888.456285
  }
]